lugia/__init__.py
lugia/core.py
lugia/dataclass.py
lugia/exceptions.py
lugia/pandas.py
lugia/polars.py
lugia/pydantic.py
lugia/pyspark.py
lugia/sqlalchemy.py
lugia/sqlmodel.py
lugia/type_converters.py
lugia/typedict.py
lugia/utils.py
lugia-0.1.1.dist-info/licenses/LICENSE
lugia-0.1.1.dist-info/METADATA
lugia-0.1.1.dist-info/WHEEL
lugia-0.1.1.dist-info/top_level.txt
lugia-0.1.1.dist-info/RECORD
