Metadata-Version: 2.4
Name: lugia
Version: 0.1.1
Summary: Universal schema converter for Python data types with optional dependencies
Author-email: Odos Matthews <odosmatthews@gmail.com>
License-Expression: MIT
Keywords: schema,converter,pydantic,pyspark,polars,pandas,dataclass,sqlalchemy
Classifier: Development Status :: 3 - Alpha
Classifier: Intended Audience :: Developers
Classifier: Programming Language :: Python :: 3
Classifier: Programming Language :: Python :: 3.9
Classifier: Programming Language :: Python :: 3.10
Classifier: Programming Language :: Python :: 3.11
Classifier: Programming Language :: Python :: 3.12
Requires-Python: >=3.9
License-File: LICENSE
Provides-Extra: pyspark
Requires-Dist: pyspark<4.0.0,>=3.5.0; extra == "pyspark"
Provides-Extra: polars
Requires-Dist: polars>=0.18.0; extra == "polars"
Provides-Extra: pandas
Requires-Dist: pandas>=1.3.0; extra == "pandas"
Provides-Extra: pydantic
Requires-Dist: pydantic<3.0.0,>=1.10.0; extra == "pydantic"
Provides-Extra: sqlmodel
Requires-Dist: sqlmodel>=0.0.8; extra == "sqlmodel"
Provides-Extra: sqlalchemy
Requires-Dist: sqlalchemy>=1.4.0; extra == "sqlalchemy"
Provides-Extra: all
Requires-Dist: pyspark<4.0.0,>=3.5.0; extra == "all"
Requires-Dist: polars>=0.18.0; extra == "all"
Requires-Dist: pandas>=1.3.0; extra == "all"
Requires-Dist: pydantic<3.0.0,>=1.10.0; extra == "all"
Requires-Dist: sqlmodel>=0.0.8; extra == "all"
Requires-Dist: sqlalchemy>=1.4.0; extra == "all"
Provides-Extra: dev
Requires-Dist: pytest>=7.0.0; extra == "dev"
Requires-Dist: pytest-cov>=4.0.0; extra == "dev"
Requires-Dist: black>=23.0.0; extra == "dev"
Requires-Dist: mypy>=1.0.0; extra == "dev"
Requires-Dist: ruff>=0.1.0; extra == "dev"
Dynamic: license-file
